<?xml version="1.0" encoding="utf-8"?>
<anime>
    <entry>
        <id>269</id>
        <title>Bleach</title>
        <english>Bleach</english>
        <synonyms>A synonym</synonyms>
        <episodes>366</episodes>
        <score>7.98</score>
        <type>TV</type>
        <status>Finished Airing</status>
        <start_date>2004-10-05</start_date>
        <end_date>2012-03-27</end_date>
        <synopsis>15-year-old Kurosaki Ichigo is not your everyday high school student. He has from as far he can remember always had the ability to see ghosts and spirits. A fateful day arrives as Ichigo encounters the shinigami Kuchiki Rukia, who saves him and his family from a Hollow at the cost of injuring herself. During this encounter, with Rukia unable to defeat the hollow she transfers her shinigami powers into Ichigo. In the aftermath, unable to continue with her job, Rukia allows Ichigo to take on the role of a shinigami in her place as they together defeat the Hollows plaguing Ichigo's town. </synopsis>
        <image>http://cdn.myanimelist.net/images/anime/3/40451.jpg</image>
    </entry>
    <entry>
        <id>762</id>
        <title>Bleach: Memories in the Rain</title>
        <english>Bleach: Memories in the Rain</english>
        <synonyms>Bleach: Jump Festa 2004</synonyms>
        <episodes>1</episodes>
        <score>7.21</score>
        <type>Special</type>
        <status>Finished Airing</status>
        <start_date>2005-06-12</start_date>
        <end_date>2005-06-12</end_date>
        <synopsis>Kurosaki Ichigo, the temporary Shinigami(Death God) for Kuchiki Rukia, discovers his mother's killer as one of the Hollows he has been hunting. He does battle with it in a prideful battle of revenge. This Special is actually a flashback of previous episodes in Bleach. After the ending credits, a short plays showing Shinigami and their Zanpakutos to &amp;quot;Number One&amp;quot; from the Bleach Soundtrack. &lt;br /&gt;
        </synopsis>
        <image>http://cdn.myanimelist.net/images/anime/5/21947.jpg</image>
    </entry>
</anime>
